
{
  "columns": [
    "path",
    "author",
    "title",
    "image",
    "description",
    "type",
    "tags"
  ],
  "data": [
    {
      "path": "/home",
      "author": "Laurel Timko",
      "title": "Home Page",
      "image": "/media_1ca6d067afb6eb9fa088723fc87e889e008fb2d77.jpeg?width=1200&format=pjpg&optimize=medium",
      "description": "Home page"
    },
    {
      "path": "/articles/a",
      "author": "Alan",
      "title": "Article A",
      "description": "Article A by Alan",
      "type": "Article",
      "tags": ["Entertainment"]
    },
    {
      "path": "/articles/b",
      "author": "Bob",
      "title": "Article B",
      "description": "Article B by Bob",
      "type": "Article",
      "tags": ["Technology"]
    },
    {
      "path": "/articles/c",
      "author": "Carl",
      "title": "Article C",
      "description": "Article C by Carl",
      "type": "Article",
      "tags": ["Travel", "Entertainment"]
    },
    {
      "path": "/articles/d",
      "author": "Darla",
      "title": "Article D",
      "description": "Article D by Darla",
      "type": "Article",
      "tags": ["Entertainment", "Technology"]
    },
    {
      "path": "/videos/e",
      "author": "Ellen",
      "title": "Video E",
      "description": "Video E by Ellen",
      "type": "Video",
      "tags": ["Entertainment"]
    },
    {
      "path": "/videos/f",
      "author": "Fred",
      "title": "Video F",
      "description": "Video F by Fred",
      "type": "Video",
      "tags": ["Technology", "Travel"]
    }
  ],
  "offset": 0,
  "limit": 2,
  "total": 2,
  ":type": "sheet"
}