{
  "definitions": [
    {
      "title": "Fragment",
      "id": "fragment",
      "plugins": {
        "da": {
          "unsafeHTML": "<div class=\"fragment\"><div><div><p><a href=\"\">Fragment URL</a></p></div></div></div>"
        }
      }
    }
  ],
  "models": [
    {
      "id": "fragment",
      "fields": [
        {
          "component": "text",
          "name": "div:nth-child(1)>div:nth-child(1)>p:nth-child(1)>a:nth-child(1)[href]",
          "label": "Fragment URL",
          "required": true
        },
        {
          "component": "text",
          "name": "div:nth-child(1)>div:nth-child(1)>p:nth-child(1)>a:nth-child(1)",
          "label": "Fragment URL Text"
        }
      ]
    }
  ],
  "filters": []
}